[
  {
    "utf16": "4e00",
    "number": "1",
    "strokes": "1",
    "character": "一",
    "onyomiKana": "イチ",
    "onyomiRomaji": "ICHI",
    "kunyomiKana": "いつ",
    "kunyomiRomaji": "itsu",
    "meaning": "uno"
  },
  {
    "utf16": "53f3",
    "number": "2",
    "strokes": "5",
    "character": "右",
    "onyomiKana": "ウ、ユウ",
    "onyomiRomaji": "U, YŪ",
    "kunyomiKana": "みぎ",
    "kunyomiRomaji": "migi",
    "meaning": "derecha"
  },
  {
    "utf16": "96e8",
    "number": "3",
    "strokes": "8",
    "character": "雨",
    "onyomiKana": "ウ",
    "onyomiRomaji": "U",
    "kunyomiKana": "あめ、あま～",
    "kunyomiRomaji": "ame, ama～",
    "meaning": "lluvia"
  },
  {
    "utf16": "5186",
    "number": "4",
    "strokes": "4",
    "character": "円",
    "onyomiKana": "エン",
    "onyomiRomaji": "EN",
    "kunyomiKana": "まる.い",
    "kunyomiRomaji": "maru.i",
    "meaning": "yen, redondo"
  },
  {
    "utf16": "738b",
    "number": "5",
    "strokes": "4",
    "character": "王",
    "onyomiKana": "オウ",
    "onyomiRomaji": "Ō",
    "kunyomiKana": "．．．",
    "kunyomiRomaji": "．．．",
    "meaning": "rey, gobernante"
  },
  {
    "utf16": "97f3",
    "number": "6",
    "strokes": "9",
    "character": "音",
    "onyomiKana": "オン、イン",
    "onyomiRomaji": "ON, IN",
    "kunyomiKana": "おと、ね",
    "kunyomiRomaji": "oto, ne",
    "meaning": "sonido"
  },
  {
    "utf16": "4e0b",
    "number": "7",
    "strokes": "3",
    "character": "下",
    "onyomiKana": "カ、ゲ",
    "onyomiRomaji": "KA, GE",
    "kunyomiKana": "した、もと、しも、さ.げる、お.りる、くだ.さる",
    "kunyomiRomaji": "shita, moto, shimo, sa.geru, o.riru, kuda.saru",
    "meaning": "debajo de, bajar"
  },
  {
    "utf16": "706b",
    "number": "8",
    "strokes": "4",
    "character": "火",
    "onyomiKana": "カ",
    "onyomiRomaji": "KA",
    "kunyomiKana": "ひ",
    "kunyomiRomaji": "hi",
    "meaning": "fuego"
  },
  {
    "utf16": "82b1",
    "number": "9",
    "strokes": "7",
    "character": "花",
    "onyomiKana": "カ",
    "onyomiRomaji": "KA",
    "kunyomiKana": "はな",
    "kunyomiRomaji": "hana",
    "meaning": "flor, florecer"
  },
  {
    "utf16": "8c9d",
    "number": "10",
    "strokes": "7",
    "character": "貝",
    "onyomiKana": "．．．",
    "onyomiRomaji": "．．．",
    "kunyomiKana": "かい",
    "kunyomiRomaji": "kai",
    "meaning": "caparazón, marisco"
  },
  {
    "utf16": "5b66",
    "number": "11",
    "strokes": "8",
    "character": "学",
    "onyomiKana": "ガク",
    "onyomiRomaji": "GAKU",
    "kunyomiKana": "まな.ぶ",
    "kunyomiRomaji": "mana.bu",
    "meaning": "aprendizaje"
  },
  {
    "utf16": "6c17",
    "number": "12",
    "strokes": "6",
    "character": "気",
    "onyomiKana": "キ、ケ",
    "onyomiRomaji": "KI, KE",
    "kunyomiKana": "．．．",
    "kunyomiRomaji": "．．．",
    "meaning": "espíritu, mente, corazón, energía"
  },
  {
    "utf16": "4e5d",
    "number": "13",
    "strokes": "2",
    "character": "九",
    "onyomiKana": "キュウ、ク",
    "onyomiRomaji": "KYŪ, KU",
    "kunyomiKana": "ここの～",
    "kunyomiRomaji": "kokono～",
    "meaning": "nueve"
  },
  {
    "utf16": "4f11",
    "number": "14",
    "strokes": "6",
    "character": "休",
    "onyomiKana": "キュウ",
    "onyomiRomaji": "KYŪ",
    "kunyomiKana": "やす.む",
    "kunyomiRomaji": "yasu.mu",
    "meaning": "descanso, descansar"
  },
  {
    "utf16": "7389",
    "number": "15",
    "strokes": "5",
    "character": "玉",
    "onyomiKana": "ギョウク",
    "onyomiRomaji": "GYŌKU",
    "kunyomiKana": "たま",
    "kunyomiRomaji": "tama",
    "meaning": "joya, bola"
  },
  {
    "utf16": "91d1",
    "number": "16",
    "strokes": "8",
    "character": "金",
    "onyomiKana": "キン、コン",
    "onyomiRomaji": "KIN, KON",
    "kunyomiKana": "かね",
    "kunyomiRomaji": "kane",
    "meaning": "oro, metal, dinero"
  },
  {
    "utf16": "7a7a",
    "number": "17",
    "strokes": "8",
    "character": "空",
    "onyomiKana": "クウ",
    "onyomiRomaji": "KŪ",
    "kunyomiKana": "そら、から",
    "kunyomiRomaji": "sora, kara",
    "meaning": "cielo, vacío"
  },
  {
    "utf16": "6708",
    "number": "18",
    "strokes": "4",
    "character": "月",
    "onyomiKana": "ゲツ、ガツ",
    "onyomiRomaji": "GETSU, GATSU",
    "kunyomiKana": "つき",
    "kunyomiRomaji": "tsuki",
    "meaning": "luna, mes"
  },
  {
    "utf16": "72ac",
    "number": "19",
    "strokes": "4",
    "character": "犬",
    "onyomiKana": "ケン",
    "onyomiRomaji": "KEN",
    "kunyomiKana": "いぬ",
    "kunyomiRomaji": "inu",
    "meaning": "perro"
  },
  {
    "utf16": "898b",
    "number": "20",
    "strokes": "7",
    "character": "見",
    "onyomiKana": "ケン",
    "onyomiRomaji": "KEN",
    "kunyomiKana": "み.る／.せる／.える",
    "kunyomiRomaji": "mi.ru/.seru/.eru",
    "meaning": "observar, ver, mostrar"
  },
  {
    "utf16": "4e94",
    "number": "21",
    "strokes": "4",
    "character": "五",
    "onyomiKana": "ゴ",
    "onyomiRomaji": "GO",
    "kunyomiKana": "いつ～",
    "kunyomiRomaji": "itsu～",
    "meaning": "cinco"
  },
  {
    "utf16": "53e3",
    "number": "22",
    "strokes": "3",
    "character": "口",
    "onyomiKana": "コウ、ク",
    "onyomiRomaji": "KŌ, KU",
    "kunyomiKana": "くち",
    "kunyomiRomaji": "kuchi",
    "meaning": "boca"
  },
  {
    "utf16": "6821",
    "number": "23",
    "strokes": "10",
    "character": "校",
    "onyomiKana": "コウ",
    "onyomiRomaji": "KŌ",
    "kunyomiKana": "．．．",
    "kunyomiRomaji": "．．．",
    "meaning": "escuela, prueba"
  },
  {
    "utf16": "5de6",
    "number": "24",
    "strokes": "5",
    "character": "左",
    "onyomiKana": "サ",
    "onyomiRomaji": "SA",
    "kunyomiKana": "ひだり",
    "kunyomiRomaji": "hidari",
    "meaning": "izquierda"
  },
  {
    "utf16": "4e09",
    "number": "25",
    "strokes": "3",
    "character": "三",
    "onyomiKana": "サン",
    "onyomiRomaji": "SAN",
    "kunyomiKana": "み～",
    "kunyomiRomaji": "mi～",
    "meaning": "tres"
  },
  {
    "utf16": "5c71",
    "number": "26",
    "strokes": "3",
    "character": "山",
    "onyomiKana": "サン",
    "onyomiRomaji": "SAN",
    "kunyomiKana": "やま",
    "kunyomiRomaji": "yama",
    "meaning": "montaña, colina"
  },
  {
    "utf16": "5b50",
    "number": "27",
    "strokes": "3",
    "character": "子",
    "onyomiKana": "シ、ス",
    "onyomiRomaji": "SHI, SU",
    "kunyomiKana": "こ",
    "kunyomiRomaji": "ko",
    "meaning": "niño/a"
  },
  {
    "utf16": "56db",
    "number": "28",
    "strokes": "5",
    "character": "四",
    "onyomiKana": "シ",
    "onyomiRomaji": "SHI",
    "kunyomiKana": "よ～、よん",
    "kunyomiRomaji": "yo～, yon",
    "meaning": "cuatro"
  },
  {
    "utf16": "7cf8",
    "number": "29",
    "strokes": "6",
    "character": "糸",
    "onyomiKana": "シ",
    "onyomiRomaji": "SHI",
    "kunyomiKana": "いと",
    "kunyomiRomaji": "ito",
    "meaning": "hilo"
  },
  {
    "utf16": "5b57",
    "number": "30",
    "strokes": "6",
    "character": "字",
    "onyomiKana": "ジ",
    "onyomiRomaji": "JI",
    "kunyomiKana": "．．．",
    "kunyomiRomaji": "．．．",
    "meaning": "letra, símbolo"
  },
  {
    "utf16": "8033",
    "number": "31",
    "strokes": "6",
    "character": "耳",
    "onyomiKana": "ジ",
    "onyomiRomaji": "JI",
    "kunyomiKana": "みみ",
    "kunyomiRomaji": "mimi",
    "meaning": "oreja"
  },
  {
    "utf16": "4e03",
    "number": "32",
    "strokes": "2",
    "character": "七",
    "onyomiKana": "シチ",
    "onyomiRomaji": "SHICHI",
    "kunyomiKana": "なな",
    "kunyomiRomaji": "nana",
    "meaning": "siete"
  },
  {
    "utf16": "8eca",
    "number": "33",
    "strokes": "7",
    "character": "車",
    "onyomiKana": "シャ",
    "onyomiRomaji": "SHA",
    "kunyomiKana": "くるま",
    "kunyomiRomaji": "kuruma",
    "meaning": "vehículo, auto, carro"
  },
  {
    "utf16": "624b",
    "number": "34",
    "strokes": "4",
    "character": "手",
    "onyomiKana": "シュ",
    "onyomiRomaji": "SHU",
    "kunyomiKana": "て",
    "kunyomiRomaji": "te",
    "meaning": "mano"
  },
  {
    "utf16": "5341",
    "number": "35",
    "strokes": "2",
    "character": "十",
    "onyomiKana": "ジュウ",
    "onyomiRomaji": "JŪ",
    "kunyomiKana": "とお",
    "kunyomiRomaji": "tō",
    "meaning": "diez"
  },
  {
    "utf16": "51fa",
    "number": "36",
    "strokes": "5",
    "character": "出",
    "onyomiKana": "シュツ",
    "onyomiRomaji": "SHUTSU",
    "kunyomiKana": "で.る、だ.す",
    "kunyomiRomaji": "de.ru, da.su",
    "meaning": "salir, sacar"
  },
  {
    "utf16": "5973",
    "number": "37",
    "strokes": "2",
    "character": "女",
    "onyomiKana": "ジョ、ニョ、ニョウ",
    "onyomiRomaji": "JO, NYO, NYŌ",
    "kunyomiKana": "おんな、め",
    "kunyomiRomaji": "onna, me",
    "meaning": "mujer"
  },
  {
    "utf16": "5c0f",
    "number": "38",
    "strokes": "3",
    "character": "小",
    "onyomiKana": "ショウ",
    "onyomiRomaji": "SHŌ",
    "kunyomiKana": "ちい.さい、こ、お～",
    "kunyomiRomaji": "chii.sai, ko, o～",
    "meaning": "pequeño"
  },
  {
    "utf16": "4e0a",
    "number": "39",
    "strokes": "3",
    "character": "上",
    "onyomiKana": "ジョウ",
    "onyomiRomaji": "JŌ",
    "kunyomiKana": "うえ、うわ～、かみ、あ.げる／.がる、のぼ.る",
    "kunyomiRomaji": "ue, uwa～, kami, a.geru/.garu, nobo.ru",
    "meaning": "arriba, encima, sobre, subir"
  },
  {
    "utf16": "68ee",
    "number": "40",
    "strokes": "12",
    "character": "森",
    "onyomiKana": "シン",
    "onyomiRomaji": "SHIN",
    "kunyomiKana": "もり",
    "kunyomiRomaji": "mori",
    "meaning": "bosque"
  },
  {
    "utf16": "4eba",
    "number": "41",
    "strokes": "2",
    "character": "人",
    "onyomiKana": "ジン、ニン",
    "onyomiRomaji": "JIN, NIN",
    "kunyomiKana": "ひと",
    "kunyomiRomaji": "hito",
    "meaning": "persona(s)"
  },
  {
    "utf16": "6c34",
    "number": "42",
    "strokes": "4",
    "character": "水",
    "onyomiKana": "スイ",
    "onyomiRomaji": "SUI",
    "kunyomiKana": "みず",
    "kunyomiRomaji": "mizu",
    "meaning": "agua"
  },
  {
    "utf16": "6b63",
    "number": "43",
    "strokes": "5",
    "character": "正",
    "onyomiKana": "セイ、ショウ",
    "onyomiRomaji": "SEI, SHŌ",
    "kunyomiKana": "ただ.し、ただ.す、まさ",
    "kunyomiRomaji": "tada.shi, tada.su, masa",
    "meaning": "correcto, apropiado"
  },
  {
    "utf16": "751f",
    "number": "44",
    "strokes": "5",
    "character": "生",
    "onyomiKana": "セイ、ショウ",
    "onyomiRomaji": "SEI, SHŌ",
    "kunyomiKana": "い.きる／.かす、う.む／.まれる、なま",
    "kunyomiRomaji": "i.kiru/.kasu, u.mu/.mareru, nama",
    "meaning": "vida, nacimiento, crecimiento"
  },
  {
    "utf16": "9752",
    "number": "45",
    "strokes": "8",
    "character": "青",
    "onyomiKana": "セイ、ショウ",
    "onyomiRomaji": "SEI, SHŌ",
    "kunyomiKana": "あお.い",
    "kunyomiRomaji": "ao.i",
    "meaning": "joven, fresco, verde/azul"
  },
  {
    "utf16": "5915",
    "number": "46",
    "strokes": "3",
    "character": "夕",
    "onyomiKana": "セキ",
    "onyomiRomaji": "SEKI",
    "kunyomiKana": "ゆう",
    "kunyomiRomaji": "yū",
    "meaning": "tarde"
  },
  {
    "utf16": "77f3",
    "number": "47",
    "strokes": "5",
    "character": "石",
    "onyomiKana": "セキ、シャク",
    "onyomiRomaji": "SEKI, SHAKU",
    "kunyomiKana": "いし",
    "kunyomiRomaji": "ishi",
    "meaning": "piedra, roca"
  },
  {
    "utf16": "8d64",
    "number": "48",
    "strokes": "7",
    "character": "赤",
    "onyomiKana": "セキ、シャク",
    "onyomiRomaji": "SEKI, SHAKU",
    "kunyomiKana": "あか.い",
    "kunyomiRomaji": "aka.i",
    "meaning": "rojo"
  },
  {
    "utf16": "5343",
    "number": "49",
    "strokes": "3",
    "character": "千",
    "onyomiKana": "セン",
    "onyomiRomaji": "SEN",
    "kunyomiKana": "ち",
    "kunyomiRomaji": "chi",
    "meaning": "mil"
  },
  {
    "utf16": "5ddd",
    "number": "50",
    "strokes": "3",
    "character": "川",
    "onyomiKana": "セン",
    "onyomiRomaji": "SEN",
    "kunyomiKana": "かわ",
    "kunyomiRomaji": "kawa",
    "meaning": "río"
  },
  {
    "utf16": "5148",
    "number": "51",
    "strokes": "6",
    "character": "先",
    "onyomiKana": "セン",
    "onyomiRomaji": "SEN",
    "kunyomiKana": "さき",
    "kunyomiRomaji": "saki",
    "meaning": "previo, preceder"
  },
  {
    "utf16": "65e9",
    "number": "52",
    "strokes": "6",
    "character": "早",
    "onyomiKana": "ソウ",
    "onyomiRomaji": "SŌ",
    "kunyomiKana": "はや.い",
    "kunyomiRomaji": "haya.i",
    "meaning": "temprano, pronto,rápido"
  },
  {
    "utf16": "8349",
    "number": "53",
    "strokes": "9",
    "character": "草",
    "onyomiKana": "ソウ",
    "onyomiRomaji": "SŌ",
    "kunyomiKana": "くさ",
    "kunyomiRomaji": "kusa",
    "meaning": "pasto, hierba, planta"
  },
  {
    "utf16": "8db3",
    "number": "54",
    "strokes": "7",
    "character": "足",
    "onyomiKana": "ソク",
    "onyomiRomaji": "SOKU",
    "kunyomiKana": "あし、た.りる",
    "kunyomiRomaji": "ashi, ta.riru",
    "meaning": "pierna, pie, suficiente, satisfacer"
  },
  {
    "utf16": "6751",
    "number": "55",
    "strokes": "7",
    "character": "村",
    "onyomiKana": "ソン",
    "onyomiRomaji": "SON",
    "kunyomiKana": "むら",
    "kunyomiRomaji": "mura",
    "meaning": "pueblo, aldea"
  },
  {
    "utf16": "5927",
    "number": "56",
    "strokes": "3",
    "character": "大",
    "onyomiKana": "ダイ、タイ",
    "onyomiRomaji": "DAI, TAI",
    "kunyomiKana": "おお.き、おお～",
    "kunyomiRomaji": "ō.ki, ō～",
    "meaning": "gran, grande"
  },
  {
    "utf16": "7537",
    "number": "57",
    "strokes": "7",
    "character": "男",
    "onyomiKana": "ダン、ナン",
    "onyomiRomaji": "DAN, NAN",
    "kunyomiKana": "おとこ",
    "kunyomiRomaji": "otoko",
    "meaning": "hombre, varon, masculino"
  },
  {
    "utf16": "7af9",
    "number": "58",
    "strokes": "6",
    "character": "竹",
    "onyomiKana": "チク",
    "onyomiRomaji": "CHIKU",
    "kunyomiKana": "たけ",
    "kunyomiRomaji": "take",
    "meaning": "bambú"
  },
  {
    "utf16": "4e2d",
    "number": "59",
    "strokes": "4",
    "character": "中",
    "onyomiKana": "チュウ",
    "onyomiRomaji": "CHŪ",
    "kunyomiKana": "なか",
    "kunyomiRomaji": "naka",
    "meaning": "en medio, dentro"
  },
  {
    "utf16": "866b",
    "number": "60",
    "strokes": "6",
    "character": "虫",
    "onyomiKana": "チュウ",
    "onyomiRomaji": "CHŪ",
    "kunyomiKana": "むし",
    "kunyomiRomaji": "mushi",
    "meaning": "insecto, bicho, gusano"
  },
  {
    "utf16": "753a",
    "number": "61",
    "strokes": "7",
    "character": "町",
    "onyomiKana": "チョウ",
    "onyomiRomaji": "CHŌ",
    "kunyomiKana": "まち",
    "kunyomiRomaji": "machi",
    "meaning": "ciudad, pueblo"
  },
  {
    "utf16": "5929",
    "number": "62",
    "strokes": "4",
    "character": "天",
    "onyomiKana": "テン",
    "onyomiRomaji": "TEN",
    "kunyomiKana": "あま～、あめ",
    "kunyomiRomaji": "ama～, ame",
    "meaning": "cielo, celestial"
  },
  {
    "utf16": "7530",
    "number": "63",
    "strokes": "5",
    "character": "田",
    "onyomiKana": "デン",
    "onyomiRomaji": "DEN",
    "kunyomiKana": "た",
    "kunyomiRomaji": "ta",
    "meaning": "campo de arroz, arrozal"
  },
  {
    "utf16": "571f",
    "number": "64",
    "strokes": "3",
    "character": "土",
    "onyomiKana": "ド、ト",
    "onyomiRomaji": "DO, TO",
    "kunyomiKana": "つち",
    "kunyomiRomaji": "tsuchi",
    "meaning": "tierra, suelo"
  },
  {
    "utf16": "4e8c",
    "number": "65",
    "strokes": "2",
    "character": "二",
    "onyomiKana": "ニ",
    "onyomiRomaji": "NI",
    "kunyomiKana": "ふた～",
    "kunyomiRomaji": "futa～",
    "meaning": "dos"
  },
  {
    "utf16": "65e5",
    "number": "66",
    "strokes": "4",
    "character": "日",
    "onyomiKana": "ニチ、ジツ",
    "onyomiRomaji": "NICHI, JITSU",
    "kunyomiKana": "ひ、～か",
    "kunyomiRomaji": "hi, ～ka",
    "meaning": "sol, día"
  },
  {
    "utf16": "5165",
    "number": "67",
    "strokes": "2",
    "character": "入",
    "onyomiKana": "ニュウ",
    "onyomiRomaji": "NYŪ",
    "kunyomiKana": "はい.る、い.れる／.る",
    "kunyomiRomaji": "hai.ru, i.reru/.ru",
    "meaning": "entrar, meter"
  },
  {
    "utf16": "5e74",
    "number": "68",
    "strokes": "6",
    "character": "年",
    "onyomiKana": "ネン",
    "onyomiRomaji": "NEN",
    "kunyomiKana": "とし",
    "kunyomiRomaji": "toshi",
    "meaning": "año"
  },
  {
    "utf16": "767d",
    "number": "69",
    "strokes": "5",
    "character": "白",
    "onyomiKana": "ハク",
    "onyomiRomaji": "HAKU",
    "kunyomiKana": "しろ.い、しら～",
    "kunyomiRomaji": "shiro.i, shira～",
    "meaning": "blanco"
  },
  {
    "utf16": "516b",
    "number": "70",
    "strokes": "2",
    "character": "八",
    "onyomiKana": "ハチ",
    "onyomiRomaji": "HACHI",
    "kunyomiKana": "や～",
    "kunyomiRomaji": "ya～",
    "meaning": "ocho"
  },
  {
    "utf16": "767e",
    "number": "71",
    "strokes": "6",
    "character": "百",
    "onyomiKana": "ヒャク",
    "onyomiRomaji": "HYAKU",
    "kunyomiKana": "．．．",
    "kunyomiRomaji": "．．．",
    "meaning": "cien"
  },
  {
    "utf16": "6587",
    "number": "72",
    "strokes": "4",
    "character": "文",
    "onyomiKana": "ブン、モン",
    "onyomiRomaji": "BUN, MON",
    "kunyomiKana": "ふみ",
    "kunyomiRomaji": "fumi",
    "meaning": "escritura, texto"
  },
  {
    "utf16": "6728",
    "number": "73",
    "strokes": "4",
    "character": "木",
    "onyomiKana": "ボク、モク",
    "onyomiRomaji": "BOKU, MOKU",
    "kunyomiKana": "き、こ",
    "kunyomiRomaji": "ki, ko",
    "meaning": "árbol, madera"
  },
  {
    "utf16": "672c",
    "number": "74",
    "strokes": "5",
    "character": "本",
    "onyomiKana": "ホン",
    "onyomiRomaji": "HON",
    "kunyomiKana": "もと",
    "kunyomiRomaji": "moto",
    "meaning": "libro, origen, verdadero, principal"
  },
  {
    "utf16": "540d",
    "number": "75",
    "strokes": "6",
    "character": "名",
    "onyomiKana": "メイ、ミョウ",
    "onyomiRomaji": "MEI, MYŌ",
    "kunyomiKana": "な",
    "kunyomiRomaji": "na",
    "meaning": "nombre, fama"
  },
  {
    "utf16": "76ee",
    "number": "76",
    "strokes": "5",
    "character": "目",
    "onyomiKana": "モク",
    "onyomiRomaji": "MOKU",
    "kunyomiKana": "め、ま",
    "kunyomiRomaji": "me, ma",
    "meaning": "ojo, mirar, malla, sufijo ordinal"
  },
  {
    "utf16": "7acb",
    "number": "77",
    "strokes": "5",
    "character": "立",
    "onyomiKana": "リツ",
    "onyomiRomaji": "RITSU",
    "kunyomiKana": "た.つ／.てる",
    "kunyomiRomaji": "ta.tsu/.teru",
    "meaning": "parar, levantar, subir"
  },
  {
    "utf16": "529b",
    "number": "78",
    "strokes": "2",
    "character": "力",
    "onyomiKana": "リョク、リキ",
    "onyomiRomaji": "RYOKU, RIKI",
    "kunyomiKana": "ちから",
    "kunyomiRomaji": "chikara",
    "meaning": "fuerza, esfuerzo"
  },
  {
    "utf16": "6797",
    "number": "79",
    "strokes": "8",
    "character": "林",
    "onyomiKana": "リン",
    "onyomiRomaji": "RIN",
    "kunyomiKana": "はやし",
    "kunyomiRomaji": "hayashi",
    "meaning": "bosque"
  },
  {
    "utf16": "516d",
    "number": "80",
    "strokes": "4",
    "character": "六",
    "onyomiKana": "ロク",
    "onyomiRomaji": "ROKU",
    "kunyomiKana": "む～",
    "kunyomiRomaji": "mu～",
    "meaning": "seis"
  }
]